compost/__init__.py
compost/compost.py
docker_compost-0.1.data/scripts/compost
docker_compost-0.1.data/scripts/docker-compost
docker_compost-0.1.data/scripts/docker-compost.py
docker_compost-0.1.dist-info/METADATA
docker_compost-0.1.dist-info/WHEEL
docker_compost-0.1.dist-info/top_level.txt
docker_compost-0.1.dist-info/RECORD
